{
    "siteName": "凤凰资讯",
    "domain": "ent.ifeng.com",
    "startURL": [
        "http://ent.ifeng.com"
    ],
    "id": "",
    "thread": "2",
    "retry": "2",
    "sleep": "800",
    "maxPageGather": "50",
    "priority": "0",
    "timeout": "5000",
    "contentReg": "",
    "contentXPath": "//div[@id='main_content']/p",
    "titleReg": "",
    "titleXPath": "",
    "categoryReg": "",
    "categoryXPath": "",
    "defaultCategory": "ent",
    "urlReg": "http://ent.ifeng.com/a/2017\\d{4}/\\d+_\\d+\\.shtml",
    "charset": "",
    "publishTimeXPath": "",
    "publishTimeReg": "<span itemprop=\"datePublished\" class=\"ss01\">(.*?)</span>",
    "publishTimeFormat": "yyyy年MM月dd日 hh:mm",
    "authorReg": "",
    "authorXPath": "//p[@class='zb_ph pc_none_new']/tidyText()",
    "imgReg": "",
    "imgXPath": "//div[@id='main_content']/p[@class='detailPic']/img/@src",
    "lang": "",
    "country": "",
    "callbackURL": [],
    "userAgent": "Mozilla/5.0 (Windows NT 5.2) AppleWebKit/534.30 (KHTML, like Gecko) Chrome/12.0.742.122 Safari/534.30",
    "proxyHost": "",
    "proxyPort": "0",
    "proxyUsername": "",
    "proxyPassword": "",
    "doNLP": true,
    "needContent": true,
    "saveCapture": true,
    "gatherFirstPage": false,
    "needTitle": false,
    "needPublishTime": false,
    "autoDetectPublishDate": false,
    "dynamicFields": [
        {
            "regex": "",
            "xpath": "//p[@class='zb_ph pc_none_new']/tidyText()",
            "name": "author",
            "need": false
        },
        {
            "regex": "",
            "xpath": "//div[@id='main_content']/p[@class='detailPic']/img/@src",
            "name": "img",
            "need": false
        }
    ],
    "staticFields": []
}